ansible_runner_http/__init__.py
ansible_runner_http/events.py
ansible_runner_http-1.0.0.dist-info/METADATA
ansible_runner_http-1.0.0.dist-info/RECORD
ansible_runner_http-1.0.0.dist-info/WHEEL
ansible_runner_http-1.0.0.dist-info/entry_points.txt
ansible_runner_http-1.0.0.dist-info/top_level.txt
