Metadata-Version: 2.1
Name: ansible-runner-http
Version: 1.0.0
Summary: UNKNOWN
Home-page: https://github.com/ansible/ansible-runner-http
Author: Red Hat Ansible
License: Apache
Platform: UNKNOWN
Requires-Dist: requests
Requires-Dist: requests-unixsocket
Requires-Dist: ansible-runner
